clean_ffmpeg_python_utils/__init__.py
clean_ffmpeg_python_utils/clean_ffmpeg_python_utils.py
clean_ffmpeg_python_utils-0.0.2.dist-info/LICENSE
clean_ffmpeg_python_utils-0.0.2.dist-info/METADATA
clean_ffmpeg_python_utils-0.0.2.dist-info/WHEEL
clean_ffmpeg_python_utils-0.0.2.dist-info/entry_points.txt
clean_ffmpeg_python_utils-0.0.2.dist-info/top_level.txt
clean_ffmpeg_python_utils-0.0.2.dist-info/RECORD
