Metadata-Version: 2.1
Name: clean-ffmpeg-python-utils
Version: 0.0.2
Summary: Easy-to-use ffmpeg python utils with simpler arguments
Home-page: https://github.com/tylerlum/clean_ffmpeg_python_utils
Author: Tyler Lum
Author-email: tylergwlum@gmail.com
Keywords: python,ffmpeg,video,audio
Classifier: Intended Audience :: Developers
Classifier: Operating System :: OS Independent
Classifier: Programming Language :: Python :: 3
License-File: LICENSE
Requires-Dist: ffmpeg-python
Requires-Dist: typed-argument-parser
